{
  "seed": 100,
  "n": 50,
  "pool_size_raw": 433,
  "pool_size_after_blocklist": 432,
  "blocklisted_pair_ids": [
    597
  ],
  "anchor_strategy": "rng_choice_size_n_replace_false",
  "selected_pair_ids": [
    1,
    41,
    76,
    101,
    115,
    124,
    139,
    158,
    181,
    203,
    207,
    229,
    242,
    273,
    279,
    285,
    299,
    317,
    344,
    349,
    350,
    363,
    376,
    377,
    382,
    385,
    403,
    441,
    478,
    481,
    494,
    500,
    513,
    540,
    566,
    567,
    570,
    635,
    667,
    677,
    684,
    688,
    698,
    729,
    756,
    763,
    769,
    774,
    777,
    789
  ]
}